LICENSE.txt
MANIFEST.in
README.rst
setup.cfg
setup.py
web_agent/__init__.py
web_agent/run.py
web_agent.egg-info/PKG-INFO
web_agent.egg-info/SOURCES.txt
web_agent.egg-info/dependency_links.txt
web_agent.egg-info/entry_points.txt
web_agent.egg-info/requires.txt
web_agent.egg-info/top_level.txt
web_agent/configuration/__init__.py
web_agent/configuration/database.yaml
web_agent/configuration/pci.ids
web_agent/rest_server/__init__.py
web_agent/rest_server/reset_server.py
web_agent/rest_server/resource/__init__.py
web_agent/rest_server/resource/dut_resource.py
web_agent/rest_server/resource/models/__init__.py
web_agent/rest_server/resource/models/ftp_server.py
web_agent/rest_server/resource/models/helper.py
web_agent/test_framework/__init__.py
web_agent/test_framework/firmware_download.py
web_agent/test_framework/state.py
web_agent/test_framework/test_base.py
web_agent/test_framework/test_case.py
web_agent/test_framework/test_pool.py
web_agent/test_framework/test_result.py
web_agent/test_framework/test_runner.py
web_agent/test_framework/test_suite.py
web_agent/test_framework/database/__init__.py
web_agent/test_framework/database/database.py
web_agent/test_framework/database/dut_database.py
web_agent/test_framework/dut/__init__.py
web_agent/test_framework/dut/agent.py
web_agent/test_framework/dut/dut.py
web_agent/test_framework/dut/slot.py
web_agent/test_framework/dut/sub_slot/__init__.py
web_agent/test_framework/dut/sub_slot/linux_slot.py
web_agent/test_framework/dut/sub_slot/oakgate_slot.py
web_agent/test_framework/test_engine/__init__.py
web_agent/test_framework/test_engine/nose_engine.py
web_agent/test_framework/test_engine/oakgate_engine.py
web_agent/test_framework/test_engine/special_parameter.py
web_agent/test_framework/upgrade_engine/__init__.py
web_agent/test_framework/upgrade_engine/serial_download.py
web_agent/tool/__init__.py
web_agent/tool/device/__init__.py
web_agent/tool/device/linux_nvme.py
web_agent/tool/device/dll/__init__.py
web_agent/tool/device/dll/buf.dll
web_agent/tool/device/dll/buf.so
web_agent/tool/device/dll/build.py
web_agent/tool/device/nvme/__init__.py
web_agent/tool/device/nvme/buf.py
web_agent/tool/device/nvme/ctype.py
